lab4/ex8/fifo.v
module fifo(clk, reset, in, push, pop, out, full);
   parameter N=4; // determines the maximum number of words in queue.
   parameter M=2; // determines the bit-width of each word, stored in the queue.

   input clk, reset, push, pop;
   input [M-1:0] in;
   output [M-1:0] out;
   output full;

   
   integer cnt;
   integer is_full;
   reg [M*N-1:0] words;
   reg [M-1:0] word_out;

   always @ (posedge clk or reset)
        begin
	// reset
	if (reset)
		begin
			cnt <= 0;
			is_full <= 0;
			words <= 0;
			word_out <= 0;
		end
	else
		begin

		// calulating is_full
		if (cnt < N)
			begin
				is_full <= 0;
			end
		else
			begin
				is_full <= 1;
			end

		// calulating word_out 
		if (cnt > 0)
			begin
				word_out <= words & ((1 << M) -1);
			end
		else
			begin
				word_out <= 0;
			end

		// Updating words and cnt

		// empty queue
		if (cnt == 0)
			begin
				if (push)
					begin
						words <= in;
						cnt <= 1;
					end
				else
					begin
						words <= words;
						cnt <= cnt;						
					end
			end
		
		// queue is partially full 
		else if (cnt < N) 
			begin
				if (push && pop) // push and pop
					begin
						words <= (words >>> M) | (in << (M * (cnt - 1)));
						cnt <= cnt;					
					end
				if (push && ~pop) // only push
					begin
						words <= words | (in << (M * cnt - 1));
						cnt <= cnt + 1;					
					end
				if (~push && pop) // only pop
					begin
						words <= (words >>> M);
						cnt <= cnt - 1;					
					end
				if (push && pop) // no push and no pop
					begin
						words <= words;
						cnt <= cnt;					
					end
			end

		// queue is full 
		else if (cnt == N)
			begin
				if (push && pop) // push and pop
					begin
						words <= (words >>> M) | (in << (M * (cnt - 1)));
						cnt <= cnt;					
					end
				if (push && ~pop) // only push
					begin
						words <= words;
						cnt <= cnt;					
					end
				if (~push && pop) // only pop
					begin
						words <= (words >>> M);
						cnt <= cnt - 1;					
					end
				if (push && pop) // no push and no pop
					begin
						words <= words;
						cnt <= cnt;					
					end
			end
		end
	end
	
	assign full = is_full;
	assign out = word_out;			

endmodule

lab4/ex8/fifo_tb.v
module main;
   reg clk, reset, push, pop;
   reg [1:0] in;
   wire [1:0] out;
   wire full;
   integer error;

   // Correct the parameter assignment
   fifo #(4,2) uut(clk, reset, in, push, pop, out, full);

   always #5 clk = ~clk;

   initial
     begin
        $dumpfile("waves.vcd");
        $dumpvars;
        clk = 1;
	error = 0;

   #10
   // test 1 - initial state, should be full = 0, out = 0, <>
   reset = 1;
   in = 0;
   push = 0;
   pop = 0;

   #10 
   if (full != 0 | out != 0)
	begin
		error <= 1;
	end

   #10
   // test 2 - pop from empty queue, should be full = 0, out = 0, <>
   reset = 0;
   in = 2;
   push = 0;
   pop = 1;

   #10 
   if (full != 0 | out != 0)
	begin
		error <= 2;
	end

   #10
   // test 3 - push to empty queue, should be full = 0, out = 0, n = 1 , <3>
   reset = 0;
   in = 3;
   push = 1;
   pop = 0;

   #10 
   if (full != 0 | out != 0)
	begin
		error <= 3;
	end

   #10
   // test 4 - pop one word from queue, should be full = 0, out = 3, n = 0 , <>
   reset = 0;
   in = 0;
   push = 0;
   pop = 1;

   #10 
   if (full != 0 | out != 3)
	begin
		error <= 4;
	end

   #10
   // test 5 - pop and push from empty queue, should be full = 0, out = 0, n = 1 , <1>
   reset = 0;
   in = 1;
   push = 1;
   pop = 1;

   #10 
   if (full != 0 | out != 0)
	begin
		error <= 5;
	end

   #10
   // test 6 - push to paritally full queue, should be full = 0, out = 1, n = 2 , <2,1>
   reset = 0;
   in = 2;
   push = 1;
   pop = 0;

   #10 
   if (full != 0 | out != 1)
	begin
		error <= 6;
	end

   #10
   // test 7 - push to paritally full queue, should be full = 0, out = 1, n = 3 , <3,2,1>
   reset = 0;
   in = 3;
   push = 1;
   pop = 0;

   #10 
   if (full != 0 | out != 1)
	begin
		error <= 7;
	end

   #10
   // test 8 - push to paritally full queue, should be full = 0, out = 1, n = 4 , <3,3,2,1>
   reset = 0;
   in = 3;
   push = 1;
   pop = 0;

   #10 
   if (full != 0 | out != 1)
	begin
		error <= 8;
	end

   #10
   // test 9 - push to a full queue, should be full = 1, out = 1, n = 4 , <3,3,2,1>
   reset = 0;
   in = 2;
   push = 1;
   pop = 0;

   #10 
   if (full != 1 | out != 1)
	begin
		error <= 9;
	end

   #10
   // test 10 - pop from a full queue, should be full = 1, out = 1, n = 3 , <3,3,2>
   reset = 0;
   in = 0;
   push = 0;
   pop = 1;

   #10 
   if (full != 1 | out != 1)
	begin
		error <= 10;
	end

   #10
   // test 11 - pop from a partially full queue, should be full = 0, out = 2, n = 2 , <3,3>
   reset = 0;
   in = 0;
   push = 0;
   pop = 1;

   #10 
   if (full != 0 | out != 2)
	begin
		error <= 11;
	end

   #10
   // test 12 - checking reset, should be full = 0, out = 0, <>
   reset = 1;
   in = 0;
   push = 0;
   pop = 0;

   #10 
   if (full != 0 | out != 0)
	begin
		error <= 12;
	end

   #10
   if (error == 0)
	begin
		$display("PASSED ALL TESTS");
	end
   else
	begin
		$display("DID NOT PASS TESTS. ERROR IN %d", error);
	end

   $finish;
   end

endmodule

lab4/ex8/waves.vcd
$date
    Dec 29, 2022  17:53:01
$end
$version
    TOOL:	xmsim(64)	21.09-s006
$end
$timescale
    1 ns
$end

$scope module main $end
$var reg       1 !    clk $end
$var reg       1 "    reset $end
$var reg       1 #    push $end
$var reg       1 $    pop $end
$var reg       2 %    in [1:0] $end
$var wire      2 &    out [1:0] $end
$var wire      1 '    full  $end
$var integer  32 (    error $end

$scope module uut $end
$var parameter 32 )    N $end
$var parameter 32 *    M $end
$var wire      1 +    clk  $end
$var wire      1 ,    reset  $end
$var wire      1 -    push  $end
$var wire      1 .    pop  $end
$var wire      2 /    in [1:0] $end
$var wire      2 &    out [1:0] $end
$var wire      1 '    full  $end
$var integer  32 0    cnt $end
$var integer  32 1    is_full $end
$var reg       8 2    words [7:0] $end
$var reg       2 3    word_out [1:0] $end
$upscope $end

$upscope $end

$enddefinitions $end
$dumpvars
b10 *
b100 )
1!
x"
x#
x$
bx %
b0 &
1'
b0 (
1+
x,
x-
x.
bx /
bx 0
b1 1
bx 2
b0 3
$end
#5
0!
0+
#10
1"
b0 %
0#
0$
1!
1+
0.
0-
b0 /
1,
b0 0
b0 1
b0 2
0'
#15
0!
0+
#20
1!
1+
#25
0!
0+
#30
0"
b10 %
1$
1!
1+
1.
b10 /
0,
#35
0!
0+
#40
1!
1+
#45
0!
0+
#50
b11 %
1#
0$
1!
1+
0.
1-
b11 /
b11 2
b1 0
#55
0!
0+
#60
1!
1+
b11 3
b1111 2
b10 0
b11 &
#65
0!
0+
#70
b0 %
0#
1$
1!
1+
1.
0-
b0 /
b11 2
b1 0
#75
0!
0+
#80
1!
1+
b0 2
b0 0
#85
0!
0+
#90
b1 %
1#
1!
1+
1-
b1 /
b0 3
b1 2
b1 0
b0 &
#95
0!
0+
#100
1!
1+
b1 3
b1 &
#105
0!
0+
#110
b10 %
0$
1!
1+
0.
b10 /
b1001 2
b10 0
#115
0!
0+
#120
1!
1+
b101001 2
b11 0
#125
0!
0+
#130
b11 %
1!
1+
b11 /
b11101001 2
b100 0
#135
0!
0+
#140
1!
1+
b1 1
1'
#145
0!
0+
#150
1!
1+
#155
0!
0+
#160
1!
1+
#165
0!
0+
#170
b10 %
1!
1+
b10 /
#175
0!
0+
#180
1!
1+
#185
0!
0+
#190
b0 %
0#
1$
1!
1+
1.
0-
b0 /
b111010 2
b11 0
#195
0!
0+
#200
1!
1+
b0 1
b10 3
b1110 2
b10 0
0'
b10 &
#205
0!
0+
#210
1!
1+
b11 2
b1 0
#215
0!
0+
#220
1!
1+
b11 3
b0 2
b0 0
b11 &
#225
0!
0+
#230
1"
0$
1!
1+
0.
1,
b0 3
b0 &
