lab4/ex7/sat_count.v
module sat_count(clk, reset, branch, taken, prediction);
   parameter N=2;
   input clk, reset, branch, taken;
   output prediction;

   reg [N-1:0] counter;


   always @ (posedge clk) begin
      if (reset)
		   counter = 0;
	  else if (branch) begin
         if (taken) begin // branch is taken
            if (counter < {2'b11}) begin // counter < 11
						counter = counter + 1;
			end
	   	 end
         else begin // branch is not taken
 			   if (counter > 0)
				   counter = counter - 1;
		 end
	  end
   end

   assign prediction = counter[N-1];

endmodule

lab4/ex7/sat_count_tb.v
module main;
reg clk, reset, branch, taken;
wire prediction;
integer error_counter;

sat_count sat_count_i(clk, reset, branch, taken, prediction);

always begin 
	#5 clk = ~clk;
end
//always@(prediction) begin
//end

initial
begin
$dumpfile("waves.vcd");
$dumpvars;
#10;
error_counter = 0;
clk = 0;
reset = 1;
branch = 0;
taken = 0;

#10;
reset = 0;
branch = 1; 
taken = 1;
#10
if (prediction != 0)
    begin
        $display("error in test 1");
        error_counter = error_counter + 1;
    end

#10;
branch = 1; 
taken = 1;
if (prediction == 0)
    begin
        $display("error in test 2");
        error_counter = error_counter + 1;
    end

#10;
branch = 1; 
taken = 1;
if (prediction == 0)
    begin
        $display("error in test 3");
        error_counter = error_counter + 1;
    end

#10;
branch = 1; 
taken = 1;
if (prediction == 0)
    begin
        $display("error in test 4");
        error_counter = error_counter + 1;
    end

#10;
branch = 0; 
taken = 0;
if (prediction == 0)
    begin
        $display("error in test 5");
        error_counter = error_counter + 1;
    end

#10;
branch = 0; 
taken = 0;
if (prediction == 0)
    begin
        $display("error in test 6");
        error_counter = error_counter + 1;
    end

#10;
branch = 1; 
taken = 0;
if (prediction == 0)
    begin
        $display("error in test 7");
        error_counter = error_counter + 1;
    end

#10;
branch = 1; 
taken = 0;
if (prediction == 0)
    begin
        $display("error in test 8");
        error_counter = error_counter + 1;
    end

#10;
branch = 1; 
taken = 0;
if (prediction != 0)
    begin
        $display("error in test 9");
        error_counter = error_counter + 1;
    end

#10;
branch = 1; 
taken = 0;
if (prediction != 0)
    begin
        $display("error in test 10");
        error_counter = error_counter + 1;
    end

#10;
branch = 1; 
taken = 0;
if (prediction != 0)
    begin
        $display("error in test 11");
        error_counter = error_counter + 1;
    end

if (error_counter == 0)
    begin
        $display("PASSED ALL TESTS");
    end
    else begin
        $display("FAILED");
    end


$finish;
end
endmodule

lab4/ex7/waves.vcd
$date
    Dec 29, 2022  15:23:41
$end
$version
    TOOL:	xmsim(64)	21.09-s006
$end
$timescale
    1 ns
$end

$scope module main $end
$var reg       1 !    clk $end
$var reg       1 "    reset $end
$var reg       1 #    branch $end
$var reg       1 $    taken $end
$var wire      1 %    prediction  $end
$var integer  32 &    error_counter $end

$scope module sat_count_i $end
$var parameter 32 '    N $end
$var wire      1 (    clk  $end
$var wire      1 )    reset  $end
$var wire      1 *    branch  $end
$var wire      1 +    taken  $end
$var wire      1 %    prediction  $end
$var reg       2 ,    counter [1:0] $end
$upscope $end

$upscope $end

$enddefinitions $end
$dumpvars
b10 '
x!
x"
x#
x$
x%
bx &
x(
x)
x*
x+
bx ,
$end
#10
b0 &
0!
1"
0#
0$
1!
0+
0*
1)
1(
b0 ,
0%
#15
0!
0(
#20
0"
1#
1$
1!
1(
1+
1*
0)
b1 ,
#25
0!
0(
#30
1!
1(
b10 ,
1%
#35
0!
0(
#40
1!
1(
b11 ,
#45
0!
0(
#50
1!
1(
#55
0!
0(
#60
1!
1(
#65
0!
0(
#70
0#
0$
1!
1(
0+
0*
#75
0!
0(
#80
1!
1(
#85
0!
0(
#90
1#
1!
1(
1*
b10 ,
#95
0!
0(
#100
1!
1(
b1 ,
0%
#105
0!
0(
#110
1!
1(
b0 ,
